LICENSE
setup.py
PyGameAuto/__init__.py
PyGameAuto.egg-info/PKG-INFO
PyGameAuto.egg-info/SOURCES.txt
PyGameAuto.egg-info/dependency_links.txt
PyGameAuto.egg-info/not-zip-safe
PyGameAuto.egg-info/requires.txt
PyGameAuto.egg-info/top_level.txt
PyGameAuto/Dm/Color.py
PyGameAuto/Dm/DmReg.dll
PyGameAuto/Dm/Mouse.py
PyGameAuto/Dm/Pic.py
PyGameAuto/Dm/Reg.py
PyGameAuto/Dm/Str.py
PyGameAuto/Dm/System.py
PyGameAuto/Dm/__init__.py
PyGameAuto/Dm/dm.dll
PyGameAuto/NetLogin/NetLogin.py
PyGameAuto/NetLogin/__init__.py
PyGameAuto/Thread/MyThread.pyd
PyGameAuto/Thread/__init__.py